LICENSE
MANIFEST.in
README.rst
setup.py
pogoiv/__init__.py
pogoiv/base_stats.py
pogoiv/cli.py
pogoiv/cp_multipliers.py
pogoiv/data.py
pogoiv/iv_calculator.py
pogoiv/iv_stats.py
pogoiv/level_dust_costs.py
pogoiv/poke_data_error.py
pogoiv.egg-info/PKG-INFO
pogoiv.egg-info/SOURCES.txt
pogoiv.egg-info/dependency_links.txt
pogoiv.egg-info/entry_points.txt
pogoiv.egg-info/not-zip-safe
pogoiv.egg-info/requires.txt
pogoiv.egg-info/top_level.txt
pogoiv/data/base_stats.tsv
pogoiv/data/cp_multipliers.tsv
pogoiv/data/level_dust_costs.tsv