Metadata-Version: 1.0
Name: pogoiv
Version: 1.1.0
Summary: Library for calculating possible pokemon GO IVs.
Home-page: http://github.com/tmwilder/pogoiv
Author: Tim Wilder
Author-email: tmwilder@gmail.com
License: MIT
Platform: UNKNOWN
